{
    "connections": [
        {
            "from_output": "output",
            "from_module": "sm1",
            "key": "9d458b1b871a1f6c",
            "to_input": "input",
            "to_module": "sm2"
        }
    ],
    "modules": [
        {
            "id": 5,
            "symtab": "/tmp/tmp3g2bhsva.ld",
            "files": [
                "/home/job/test/sancus/reactive/sm1.c"
            ],
            "node": "node1",
            "key": "245355d57e6ae413",
            "name": "sm1",
            "binary": "/tmp/tmpw5u59raa.elf",
            "type": "sancus"
        },
        {
            "id": 6,
            "symtab": "/tmp/tmpycjlxdj5.ld",
            "files": [
                "/home/job/test/sancus/reactive/sm2.c"
            ],
            "node": "node1",
            "key": "4064dc064c4906bd",
            "name": "sm2",
            "binary": "/tmp/tmpgj1yp6ox.elf",
            "type": "sancus"
        }
    ],
    "nodes": [
        {
            "ip_address": "192.168.0.2",
            "name": "node1",
            "vendor_id": 4660,
            "type": "sancus",
            "vendor_key": "4078d505d82099ba"
        }
    ]
}